[
    {
        "id":1,
        "img":"레벨.jpg",
        "title":"집밥으로 맛있게 건강 챙기기. 냉장고에 들어있던 바질이랑 캐비어 정도는 있으시죠?",
        "writer":"집밥금선생",
        "comment":3,
        "list":"#"
    },
    {
        "id":2,
        "img":"best_list_2.jfif",
        "title":"올림픽까지 나와서 판촉행위 하는 선수.jpg",
        "writer":"도탁스",
        "comment":6,
        "list":"#"
    },
    {
        "id":3,
        "img":"best_list_4.webp",
        "title":"엄태구 오랜 짝사랑녀 앞에서 머리 하얘져 침묵…재운 건 아니다 (유퀴즈) [MK★TV픽]",
        "writer":"여성시대",
        "comment":2,
        "list":"#"
    },
    {
        "id":4,
        "img":"best_list_3.jfif",
        "title":"너무 비쌌지만 퀄리티는 최고여서 매니아층 꽤 있던 초코 과자",
        "writer":"소울드레서",
        "comment":3,
        "list":"#"
    },
    {
        "id":5,
        "img":"best_list_5.jfif",
        "title":"흥행 대박일 것 같은 k 멀티버스 .jpg",
        "writer":"도탁스",
        "comment":10,
        "list":"#"
    },
    {
        "id":6,
        "img":"best_list_6.jfif",
        "title":"최근 사극 분장한 조정석",
        "writer":"여성시대",
        "comment":5,
        "list":"#"
    },
    {
        "id":7,
        "img":"best_list_2.jfif",
        "title":"올림픽까지 나와서 판촉행위 하는 선수.jpg",
        "writer":"도탁스",
        "comment":6,
        "list":"#"
    },
    {
        "id":8,
        "img":"best_list_2.jfif",
        "title":"올림픽까지 나와서 판촉행위 하는 선수.jpg",
        "writer":"도탁스",
        "comment":6,
        "list":"#"
    },
    {
        "id":9,
        "img":"best_list_2.jfif",
        "title":"올림픽까지 나와서 판촉행위 하는 선수.jpg",
        "writer":"도탁스",
        "comment":6,
        "list":"#"
    },
    {
        "id":10,
        "img":"best_list_2.jfif",
        "title":"올림픽까지 나와서 판촉행위 하는 선수.jpg",
        "writer":"도탁스",
        "comment":6,
        "list":"#"
    }
]